LICENSE
README.md
setup.cfg
setup.py
sentry_googlechat/__init__.py
sentry_googlechat/plugin.py
vend_sentry_google_chat.egg-info/PKG-INFO
vend_sentry_google_chat.egg-info/SOURCES.txt
vend_sentry_google_chat.egg-info/dependency_links.txt
vend_sentry_google_chat.egg-info/entry_points.txt
vend_sentry_google_chat.egg-info/top_level.txt