Metadata-Version: 2.1
Name: vend-sentry-google-chat
Version: 10.0.1
Summary: A Sentry plugin which posts notifications to Google Chat (https://gsuite.google.com/products/chat/).
Home-page: https://github.com/jweslley/sentry-googlechat
Author: Jonhnny Weslley
Author-email: jw@jonhnnyweslley.net
License: MIT
Classifier: Intended Audience :: Developers
Classifier: Intended Audience :: System Administrators
Classifier: License :: OSI Approved :: MIT License
Classifier: Operating System :: OS Independent
Classifier: Topic :: Software Development
Classifier: Topic :: System :: Monitoring
License-File: LICENSE
